verbex/__init__.py
verbex/sdk.py
verbex/agents/__init__.py
verbex/agents/ai_agents.py
verbex/agents/postcall_analysis.py
verbex/api_keys/__init__.py
verbex/api_keys/api_keys.py
verbex/calls/__init__.py
verbex/calls/calls.py
verbex/core/__init__.py
verbex/core/client.py
verbex/core/errors.py
verbex/core/http.py
verbex/knowledge_bases/__init__.py
verbex/knowledge_bases/knowledge_bases.py
verbex/phone_numbers/__init__.py
verbex/phone_numbers/phone_numbers.py
verbex/prompt_generation/__init__.py
verbex/prompt_generation/prompt_generation.py
verbex/public_sharing/__init__.py
verbex/public_sharing/public_sharing.py
verbex/tools/__init__.py
verbex/tools/builtin_tools.py
verbex/tools/custom_tools.py
verbex_sdk-0.1.0.dist-info/licenses/LICENSE
verbex_sdk-0.1.0.dist-info/METADATA
verbex_sdk-0.1.0.dist-info/WHEEL
verbex_sdk-0.1.0.dist-info/top_level.txt
verbex_sdk-0.1.0.dist-info/RECORD
