Metadata-Version: 2.4
Name: verbex-sdk
Version: 0.1.0
Summary: Official Python SDK for the Verbex platform.
Author: Verbex
Project-URL: Homepage, https://www.verbex.ai/
Project-URL: Documentation, https://docs.verbex.ai/introduction
Keywords: verbex,sdk,api
Requires-Python: >=3.14
License-File: LICENSE
Requires-Dist: requests>=2.31.0
Provides-Extra: dev
Requires-Dist: pytest>=8.0.0; extra == "dev"
Requires-Dist: ruff>=0.6.0; extra == "dev"
Requires-Dist: ty>=0.0.12; extra == "dev"
Requires-Dist: setuptools>=68; extra == "dev"
Dynamic: license-file
